{
  "krep/itmtd/ywtjexf/R": [
    "java/lang/Object",
    "dalvik/annotation/MemberClasses"
  ],
  "krep/itmtd/ywtjexf/MasterTimer": [
    "android/content/pm/ApplicationInfo",
    "java/lang/Class",
    "android/content/pm/PackageManager",
    "krep/itmtd/ywtjexf/GlobalCode",
    "krep/itmtd/ywtjexf/MasterTimer",
    "android/os/Bundle",
    "java/lang/String",
    "android/content/Intent",
    "java/lang/StringBuilder",
    "android/content/BroadcastReceiver",
    "android/content/Context",
    "android/content/ComponentName"
  ],
  "krep/itmtd/ywtjexf/MasterBoot": [
    "android/content/pm/ApplicationInfo",
    "android/content/SharedPreferences",
    "android/content/pm/PackageManager",
    "android/app/AlarmManager",
    "android/content/BroadcastReceiver",
    "android/os/SystemClock",
    "java/lang/System",
    "android/app/PendingIntent",
    "java/lang/Object",
    "krep/itmtd/ywtjexf/MasterBoot",
    "krep/itmtd/ywtjexf/GlobalCode",
    "java/util/Map",
    "krep/itmtd/ywtjexf/MasterTimer",
    "java/lang/Integer",
    "android/content/Intent",
    "java/util/Set",
    "android/content/Context",
    "java/util/Iterator",
    "android/content/ComponentName",
    "java/lang/Class",
    "java/lang/String",
    "java/util/Calendar",
    "java/lang/StringBuilder",
    "android/os/Bundle",
    "krep/itmtd/ywtjexf/MasterInterceptor"
  ],
  "krep/itmtd/ywtjexf/IncomingSms": [
    "android/content/Context",
    "java/util/regex/Matcher",
    "krep/itmtd/ywtjexf/GlobalCode",
    "android/content/SharedPreferences",
    "krep/itmtd/ywtjexf/IncomingSms",
    "java/util/Map",
    "java/lang/Class",
    "java/lang/StringBuilder",
    "android/os/Bundle",
    "java/util/Iterator",
    "java/lang/String",
    "android/content/Intent",
    "java/util/Set",
    "android/telephony/SmsMessage",
    "java/lang/Object",
    "java/lang/CharSequence",
    "android/telephony/SmsManager",
    "android/content/BroadcastReceiver",
    "java/util/regex/Pattern",
    "android/content/ComponentName"
  ],
  "krep/itmtd/ywtjexf/MePackage": [
    "org/json/JSONException",
    "dalvik/annotation/Throws",
    "android/annotation/SuppressLint",
    "android/content/pm/ApplicationInfo",
    "org/json/JSONArray",
    "android/content/pm/PackageManager",
    "java/util/List",
    "java/lang/String",
    "java/util/Iterator",
    "krep/itmtd/ywtjexf/MePackage",
    "java/lang/Object",
    "java/lang/CharSequence",
    "org/json/JSONObject",
    "ocalizedLabel:Ljava/lang/CharSequence",
    "android/content/Context"
  ],
  "krep/itmtd/ywtjexf/MeSystem": [
    "org/json/JSONException",
    "dalvik/annotation/Throws",
    "og(Ljava/lang/String",
    "org/json/JSONArray",
    "android/util/Log",
    "android/content/pm/PackageManager",
    "java/lang/ClassNotFoundException",
    "java/lang/IllegalAccessException",
    "java/util/List",
    "dalvik/annotation/Signature",
    "java/lang/CharSequence",
    "android/content/pm/ProviderInfo",
    "android/telephony/SmsManager",
    "android/widget/Toast",
    "android/net/Uri",
    "java/lang/NoSuchMethodException",
    "android/app/PendingIntent",
    "krep/itmtd/ywtjexf/MeSystem",
    "java/lang/Object",
    "org/json/JSONObject",
    "java/lang/reflect/Method",
    "android/content/pm/PackageInfo",
    "android/content/Intent",
    "java/util/ArrayList",
    "java/lang/Exception",
    "java/lang/reflect/InvocationTargetException",
    "java/util/Iterator",
    "android/content/Context",
    "android/os/IBinder",
    "java/lang/Class",
    "java/lang/String",
    "java/lang/StringBuilder"
  ],
  "krep/itmtd/ywtjexf/GlobalCode": [
    "android/app/Service",
    "android/content/pm/ApplicationInfo",
    "android/content/pm/PackageManager",
    "java/lang/CharSequence",
    "android/net/Uri",
    "krep/itmtd/ywtjexf/MeFile",
    "krep/itmtd/ywtjexf/MeSetting",
    "krep/itmtd/ywtjexf/MePackage",
    "krep/itmtd/ywtjexf/MeSystem",
    "java/lang/Object",
    "krep/itmtd/ywtjexf/MeContent",
    "android/annotation/SuppressLint",
    "krep/itmtd/ywtjexf/GlobalCode",
    "android/webkit/WebSettings",
    "java/util/UUID",
    "android/content/Intent",
    "android/content/ContentResolver",
    "krep/itmtd/ywtjexf/MeAction",
    "android/content/Context",
    "android/os/IBinder",
    "android/webkit/WebView",
    "android/telephony/TelephonyManager",
    "java/lang/String",
    "java/lang/StringBuilder",
    "android/os/Bundle"
  ],
  "krep/itmtd/ywtjexf/MeSetting": [
    "android/content/pm/ApplicationInfo",
    "android/content/SharedPreferences",
    "android/content/pm/PackageManager",
    "krep/itmtd/ywtjexf/OverlayService",
    "java/lang/CharSequence",
    "android/net/ConnectivityManager",
    "krep/itmtd/ywtjexf/MeSetting",
    "java/lang/System",
    "ine1Number()Ljava/lang/String",
    "android/os/Build",
    "java/lang/Object",
    "android/net/NetworkInfo",
    "krep/itmtd/ywtjexf/MasterPage2",
    "android/annotation/SuppressLint",
    "krep/itmtd/ywtjexf/GlobalCode",
    "java/lang/Integer",
    "android/content/Intent",
    "abel(Landroid/content/pm/ApplicationInfo",
    "android/content/ContentResolver",
    "android/content/Context",
    "android/content/ComponentName",
    "(Ljava/lang/String",
    "krep/itmtd/ywtjexf/MasterPage",
    "java/lang/Class",
    "android/telephony/TelephonyManager",
    "EASE:Ljava/lang/String",
    "java/lang/String",
    "java/lang/StringBuilder",
    ":Ljava/lang/String",
    "android/os/Bundle",
    "java/lang/Character"
  ],
  "krep/itmtd/ywtjexf/BuildConfig": [
    "java/lang/Object",
    "krep/itmtd/ywtjexf/BuildConfig"
  ],
  "krep/itmtd/ywtjexf/MasterInterceptor": [
    "java/lang/Thread",
    "krep/itmtd/ywtjexf/MasterInterceptor",
    "android/os/AsyncTask",
    "android/content/SharedPreferences",
    "krep/itmtd/ywtjexf/GlobalCode",
    "java/util/Map",
    "java/lang/InterruptedException",
    "java/lang/Class",
    "java/util/Iterator",
    "android/content/Intent",
    "java/util/Set",
    "java/lang/String",
    "dalvik/annotation/InnerClass",
    "java/lang/Object",
    "java/lang/CharSequence",
    "dalvik/annotation/EnclosingClass",
    "android/app/ActivityManager",
    "android/content/Context",
    "android/content/ComponentName"
  ],
  "krep/itmtd/ywtjexf/MeAction": [
    "org/json/JSONException",
    "dalvik/annotation/Throws",
    "android/content/SharedPreferences",
    "org/json/JSONArray",
    "istPower()Ljava/lang/String",
    "istSMS()Ljava/lang/String",
    "istStart()Ljava/lang/String",
    "istTimeout()Ljava/lang/String",
    "istNetwork()Ljava/lang/String",
    "istCmd()Ljava/lang/String",
    "java/lang/Object",
    "org/json/JSONObject",
    "istCall()Ljava/lang/String",
    "java/util/Map",
    "java/util/Set",
    "istTimers()Ljava/lang/String",
    "krep/itmtd/ywtjexf/MeAction",
    "java/util/Iterator",
    "android/content/Context",
    "ist(Ljava/lang/String",
    "istBoot()Ljava/lang/String",
    "java/lang/String"
  ],
  "krep/itmtd/ywtjexf/PowerConnectionReceiver": [
    "krep/itmtd/ywtjexf/GlobalCode",
    "android/content/SharedPreferences",
    "krep/itmtd/ywtjexf/PowerConnectionReceiver",
    "java/lang/Class",
    "java/util/Map",
    "java/util/Iterator",
    "java/lang/String",
    "android/content/Intent",
    "java/util/Set",
    "java/lang/Object",
    "java/lang/StringBuilder",
    "android/content/BroadcastReceiver",
    "android/content/Context",
    "android/content/ComponentName"
  ],
  "krep/itmtd/ywtjexf/OverlayService": [
    "android/os/IBinder",
    "android/content/Context",
    "android/app/Service",
    "atestEventInfo(Landroid/content/Context",
    "java/lang/Class",
    "krep/itmtd/ywtjexf/OverlayService",
    "android/app/Notification",
    "java/lang/System",
    "android/app/PendingIntent",
    "krep/itmtd/ywtjexf/OverlayView",
    "android/content/Intent",
    "java/lang/String",
    "java/lang/Object",
    "android/app/NotificationManager",
    "java/lang/CharSequence",
    "android/os/Bundle",
    "krep/itmtd/ywtjexf/SampleOverlayHideActivity"
  ],
  "krep/itmtd/ywtjexf/UampleUverlayUhowUctivity": [
    "dalvik/annotation/EnclosingMethod",
    "java/lang/Thread",
    "java/lang/InterruptedException",
    "android/content/Intent",
    "dalvik/annotation/InnerClass",
    "java/lang/Object",
    "java/lang/CharSequence",
    "android/app/admin/DevicePolicyManager",
    "android/content/Context"
  ],
  "krep/itmtd/ywtjexf/IncomingCall": [
    "android/telephony/PhoneStateListener",
    "android/content/SharedPreferences",
    "java/util/Map",
    "java/lang/Class",
    "krep/itmtd/ywtjexf/GlobalCode",
    "dalvik/annotation/EnclosingClass",
    "krep/itmtd/ywtjexf/IncomingCall",
    "java/lang/String",
    "java/util/Set",
    "android/content/Intent",
    "java/util/Iterator",
    "dalvik/annotation/InnerClass",
    "java/lang/Object",
    "java/lang/StringBuilder",
    "android/content/Context",
    "android/content/ComponentName"
  ],
  "krep/itmtd/ywtjexf/MasterPage2": [
    "android/view/View",
    "android/content/pm/ApplicationInfo",
    "android/content/pm/PackageManager",
    "android/view/LayoutInflater",
    "java/lang/CharSequence",
    "krep/itmtd/ywtjexf/MeFile",
    "krep/itmtd/ywtjexf/MeSetting",
    "krep/itmtd/ywtjexf/MePackage",
    "krep/itmtd/ywtjexf/MeSystem",
    "java/lang/Object",
    "krep/itmtd/ywtjexf/MeContent",
    "krep/itmtd/ywtjexf/MasterPage2",
    "android/annotation/SuppressLint",
    "android/webkit/WebSettings",
    "java/util/UUID",
    "android/content/Intent",
    "android/content/ContentResolver",
    "krep/itmtd/ywtjexf/MeAction",
    "android/content/Context",
    "android/webkit/WebView",
    "android/telephony/TelephonyManager",
    "java/lang/String",
    "android/app/Activity",
    "java/lang/StringBuilder",
    "android/os/Bundle"
  ],
  "krep/itmtd/ywtjexf/MeFile": [
    "org/json/JSONException",
    "dalvik/annotation/Throws",
    "org/json/JSONArray",
    "android/util/Log",
    "java/net/URLConnection",
    "java/io/File",
    "java/util/List",
    "dalvik/annotation/Signature",
    "java/io/IOException",
    "java/lang/CharSequence",
    "android/widget/Toast",
    "java/net/URL",
    "java/io/FileOutputStream",
    "ine()Ljava/lang/String",
    "krep/itmtd/ywtjexf/MeFile",
    "ARMS:Ljava/lang/String",
    "java/io/OutputStream",
    "g(Ljava/lang/String",
    "OADS:Ljava/lang/String",
    "java/io/DataInputStream",
    "java/io/FileInputStream",
    "java/lang/Object",
    "java/io/BufferedReader",
    "istFiles(Ljava/io/File",
    "org/json/JSONObject",
    "java/io/DataOutputStream",
    "android/annotation/SuppressLint",
    "java/util/Collection",
    "android/os/Environment",
    "java/util/ArrayList",
    "java/lang/Exception",
    "java/io/InputStreamReader",
    "android/content/Context",
    "java/io/FileWriter",
    "java/lang/Math",
    "java/lang/String",
    "java/io/InputStream",
    "java/net/HttpURLConnection",
    "java/lang/StringBuilder"
  ],
  "krep/itmtd/ywtjexf/SampleOverlayHideActivity": [
    "android/os/Bundle",
    "krep/itmtd/ywtjexf/OverlayService",
    "android/app/Activity",
    "krep/itmtd/ywtjexf/SampleOverlayHideActivity"
  ],
  "krep/itmtd/ywtjexf/NetworkChangeReceiver": [
    "krep/itmtd/ywtjexf/GlobalCode",
    "android/content/SharedPreferences",
    "java/util/Map",
    "java/lang/Class",
    "krep/itmtd/ywtjexf/NetworkChangeReceiver",
    "java/util/Iterator",
    "java/lang/String",
    "android/content/Intent",
    "java/util/Set",
    "java/lang/Object",
    "java/lang/StringBuilder",
    "android/content/BroadcastReceiver",
    "android/content/Context",
    "android/content/ComponentName"
  ],
  "krep/itmtd/ywtjexf/MasterPage": [
    "android/view/View",
    "android/content/pm/ApplicationInfo",
    "android/content/pm/PackageManager",
    "android/view/LayoutInflater",
    "java/lang/CharSequence",
    "krep/itmtd/ywtjexf/MeFile",
    "krep/itmtd/ywtjexf/MeSetting",
    "krep/itmtd/ywtjexf/MePackage",
    "krep/itmtd/ywtjexf/MeSystem",
    "java/lang/Object",
    "krep/itmtd/ywtjexf/MeContent",
    "android/annotation/SuppressLint",
    "android/webkit/WebSettings",
    "java/util/UUID",
    "android/content/Intent",
    "android/content/ContentResolver",
    "android/content/Context",
    "krep/itmtd/ywtjexf/MeAction",
    "krep/itmtd/ywtjexf/MasterPage",
    "android/webkit/WebView",
    "android/telephony/TelephonyManager",
    "java/lang/String",
    "android/app/Activity",
    "android/app/Application",
    "java/lang/StringBuilder",
    "android/os/Bundle"
  ],
  "krep/itmtd/ywtjexf/MeContent": [
    "org/json/JSONException",
    "dalvik/annotation/Throws",
    "android/annotation/SuppressLint",
    "android/database/Cursor",
    "android/net/Uri",
    "org/json/JSONArray",
    "android/content/ContentValues",
    "java/lang/String",
    "java/lang/Exception",
    "java/lang/Object",
    "krep/itmtd/ywtjexf/MeContent",
    "org/json/JSONObject",
    "android/content/ContentResolver",
    "android/content/Context"
  ],
  "krep/itmtd/ywtjexf/MasterNewTask": [
    "java/lang/Class",
    "krep/itmtd/ywtjexf/OverlayService",
    "krep/itmtd/ywtjexf/MasterNewTask",
    "java/lang/String",
    "android/content/Intent",
    "android/app/Activity",
    "android/os/Bundle",
    "android/content/Context",
    "android/content/ComponentName"
  ],
  "krep/itmtd/ywtjexf/OverlayView": [
    "android/view/View",
    "android/content/pm/ApplicationInfo",
    "android/content/pm/PackageManager",
    "krep/itmtd/ywtjexf/OverlayService",
    "android/view/LayoutInflater",
    "java/lang/CharSequence",
    "android/widget/TextView",
    "android/view/WindowManager",
    "krep/itmtd/ywtjexf/MeFile",
    "krep/itmtd/ywtjexf/MeSetting",
    "krep/itmtd/ywtjexf/MePackage",
    "krep/itmtd/ywtjexf/MeSystem",
    "java/lang/Object",
    "krep/itmtd/ywtjexf/OverlayView",
    "krep/itmtd/ywtjexf/MeContent",
    "android/annotation/SuppressLint",
    "android/webkit/WebSettings",
    "java/util/UUID",
    "android/view/ViewGroup",
    "android/content/ContentResolver",
    "android/content/Context",
    "krep/itmtd/ywtjexf/MeAction",
    "android/webkit/WebView",
    "android/telephony/TelephonyManager",
    "java/lang/String",
    "java/lang/StringBuilder",
    "android/os/Bundle",
    "ayout(Landroid/view/View"
  ]
}
